protoform/__init__.py
protoform/cli.py
protoform/data.py
protoform/graph.py
protoform/io.py
protoform/modules/common.py
protoform/modules/compute_age.py
protoform/modules/io/common.py
protoform/modules/io/node.py
protoform/modules/io/sink/__init__.py
protoform/modules/io/sink/csv.py
protoform/modules/io/sink/manifold.py
protoform/modules/io/sink/parquet.py
protoform/modules/io/sink/snowflake.py
protoform/modules/io/sink/sql.py
protoform/modules/io/source/__init__.py
protoform/modules/io/source/csv.py
protoform/modules/io/source/parquet.py
protoform/modules/io/source/sql.py
protoform/modules/io/utils.py
protoform/modules/misc.py
protoform/modules/operator/__init__.py
protoform/modules/operator/common.py
protoform/modules/operator/dynamic_load_code.py
protoform/modules/operator/filter_table.py
protoform/modules/operator/hipaa_deidentifier.py
protoform/modules/operator/join_tables.py
protoform/modules/operator/load_dataset.py
protoform/modules/operator/normalize_string.py
protoform/modules/operator/pivot_table.py
protoform/modules/operator/schemas.py
protoform/modules/operator/shape_data_graph.py
protoform/modules/operator/shape_graph.py
protoform/modules/operator/subset_data_by_percentage.py
protoform/modules/operator/unpivot_table.py
protoform/modules/operator/write_dataset.py
protoform/operator.py
protoform/task.py
protoform/utils.py
protoform-0.0.2.dist-info/METADATA
protoform-0.0.2.dist-info/WHEEL
protoform-0.0.2.dist-info/entry_points.txt
protoform-0.0.2.dist-info/licenses/LICENSE
protoform-0.0.2.dist-info/RECORD
