Metadata-Version: 2.4
Name: protoform
Version: 0.0.2
Summary: shaping data
License-File: LICENSE
Author: michael pan
Author-email: michael@dataxight.com
Requires-Python: >=3.10,<3.13
Classifier: Programming Language :: Python :: 3
Classifier: Programming Language :: Python :: 3.10
Classifier: Programming Language :: Python :: 3.11
Classifier: Programming Language :: Python :: 3.12
Provides-Extra: mysql
Provides-Extra: pyathena
Provides-Extra: snowflake
Requires-Dist: ciso8601 (>=2.3.1)
Requires-Dist: connectorx (>=0.4.3)
Requires-Dist: daft (>=0.6.2,<0.7.0)
Requires-Dist: impyla (>=0.21.0,<0.22.0)
Requires-Dist: pandas (>=2.3.1,<3.0.0)
Requires-Dist: pydantic (>=2.11.7,<3.0.0)
Requires-Dist: pyhive (>=0.7.0,<0.8.0)
Requires-Dist: rustworkx (>=0.16.0)
Requires-Dist: snowflake (>=1.7.0,<2.0.0) ; extra == "snowflake"
Requires-Dist: sqlalchemy (>=2.0.41,<3.0.0)
Requires-Dist: sqlglot (>=26.19.0)
Requires-Dist: uritools (>=5.0.0)
Project-URL: Documentation, https://github.com/dataxight/protoform
Project-URL: Repository, https://github.com/dataxight/protoform
